rover_connect2_module/__init__.py
rover_connect2_module/rover_connect.py
rover_connect2_module-0.1.2.dist-info/LICENSE
rover_connect2_module-0.1.2.dist-info/METADATA
rover_connect2_module-0.1.2.dist-info/WHEEL
rover_connect2_module-0.1.2.dist-info/top_level.txt
rover_connect2_module-0.1.2.dist-info/RECORD
